payment/__init__.py
payment/__version__.py
payment/nestpay.py
payment/utils.py
nestpay-0.0.3.dist-info/METADATA
nestpay-0.0.3.dist-info/WHEEL
nestpay-0.0.3.dist-info/top_level.txt
nestpay-0.0.3.dist-info/RECORD
